hotlog/__init__.py
hotlog/config.py
hotlog/filtering.py
hotlog/formatting.py
hotlog/live.py
hotlog/logger.py
hotlog/matchers.py
hotlog/py.typed
hotlog/rendering.py
hotlog/verbosity.py
hotlog/version.py
hotlog-0.1.3.dist-info/METADATA
hotlog-0.1.3.dist-info/WHEEL
hotlog-0.1.3.dist-info/entry_points.txt
hotlog-0.1.3.dist-info/licenses/LICENSE
hotlog-0.1.3.dist-info/RECORD
