Metadata-Version: 2.4
Name: hotlog
Version: 0.1.3
Summary: cli loggging utilities
Author: hotdog-werx
License-Expression: MIT
License-File: LICENSE
Requires-Python: >=3.11
Requires-Dist: pyyaml<7,>=6.0
Requires-Dist: rich<15,>=14.0.0
Requires-Dist: structlog<26,>=25.4.0
